pdistributionpy/Binomialdistribution.py
pdistributionpy/Gaussiandistribution.py
pdistributionpy/Generaldistribution.py
pdistributionpy/__init__.py
pdistributionpy/numbers.txt
pdistributionpy/numbers_binomial.txt
pdistributionpy/test.py
pdistributionpy-0.2.dist-info/WHEEL
pdistributionpy-0.2.dist-info/METADATA
pdistributionpy-0.2.dist-info/RECORD
